aclick/__init__.py
aclick/_version.py
aclick/configuration.py
aclick/core.py
aclick/decorators.py
aclick/types.py
aclick/utils.py
aclick-0.2.3.dist-info/METADATA
aclick-0.2.3.dist-info/WHEEL
aclick-0.2.3.dist-info/top_level.txt
aclick-0.2.3.dist-info/RECORD
