Metadata-Version: 2.1
Name: aclick
Version: 0.2.3
Summary: UNKNOWN
Home-page: UNKNOWN
Author: Jonáš Kulhánek
Author-email: jonas.kulhanek@live.com
License: MIT License
Platform: UNKNOWN
Requires-Python: >=3.7
Requires-Dist: click (>=8.0.3)
Requires-Dist: docstring-parser (>=0.14.1)
Requires-Dist: typing-extensions (>=3.6.4) ; python_version < "3.8"
